databricks_test/__init__.py
databricks_test-0.0.4.dist-info/METADATA
databricks_test-0.0.4.dist-info/WHEEL
databricks_test-0.0.4.dist-info/top_level.txt
databricks_test-0.0.4.dist-info/RECORD
