Metadata-Version: 2.1
Name: databricks-test
Version: 0.0.4
Summary: Unit testing and mocking for Databricks
Home-page: https://github.com/microsoft/DataOps
Author: Alexandre Gattiker
Author-email: algattik@microsoft.com
License: UNKNOWN
Platform: UNKNOWN
Classifier: Programming Language :: Python :: 3
Classifier: License :: OSI Approved :: MIT License
Classifier: Operating System :: OS Independent
